charmcli/__init__.py
charmcli/__main__.py
charmcli/excepthook.py
charmcli/header.py
charmcli/hyperlink.py
charmcli/text_styler.py
charmcli-0.1.3.dist-info/licenses/LICENSE
charmcli-0.1.3.dist-info/METADATA
charmcli-0.1.3.dist-info/WHEEL
charmcli-0.1.3.dist-info/entry_points.txt
charmcli-0.1.3.dist-info/top_level.txt
charmcli-0.1.3.dist-info/RECORD
