Metadata-Version: 2.4
Name: charmcli
Version: 0.1.3
Summary: Charmcli, build great CLIs. Easy to code. Based on Python type hints.
Author-email: callbackcat <hello@chamanbudhathoki.com.np>
Project-URL: Homepage, https://github.com/chamanbravo/charmcli
Project-URL: Repository, https://github.com/chamanbravo/charmcli
Project-URL: Issues, https://github.com/chamanbravo/charmcli/issues
Classifier: Intended Audience :: Information Technology
Classifier: Intended Audience :: System Administrators
Classifier: Operating System :: OS Independent
Classifier: Programming Language :: Python :: 3
Classifier: Programming Language :: Python
Classifier: Topic :: Software Development :: Libraries :: Application Frameworks
Classifier: Topic :: Software Development :: Libraries :: Python Modules
Classifier: Topic :: Software Development :: Libraries
Classifier: Topic :: Software Development
Classifier: Typing :: Typed
Classifier: Intended Audience :: Developers
Classifier: License :: OSI Approved :: MIT License
Requires-Python: >=3.11
License-File: LICENSE
Dynamic: license-file
